{
  "db_name": "PostgreSQL",
  "query": "\n                SELECT created_at\n                FROM likes\n                WHERE user_id = $1 AND content_type = $2 AND content_id = $3\n                ",
  "describe": {
    "columns": [
      {
        "ordinal": 0,
        "name": "created_at",
        "type_info": "Timestamptz"
      }
    ],
    "parameters": {
      "Left": [
        "Uuid",
        "Text",
        "Uuid"
      ]
    },
    "nullable": [
      false
    ]
  },
  "hash": "7c45000bd59d2a994cdd5cb44c8fcf03bd0a45bab72a27c474ad6d8ce78c97eb"
}
